pyattck_data_models/__init__.py
pyattck_data_models/__main__.py
pyattck_data_models/actor.py
pyattck_data_models/attack.py
pyattck_data_models/base.py
pyattck_data_models/control.py
pyattck_data_models/datacomponent.py
pyattck_data_models/datasource.py
pyattck_data_models/definition.py
pyattck_data_models/generated.py
pyattck_data_models/identity.py
pyattck_data_models/malware.py
pyattck_data_models/matrix.py
pyattck_data_models/mitigation.py
pyattck_data_models/nist.py
pyattck_data_models/py.typed
pyattck_data_models/relationship.py
pyattck_data_models/tactic.py
pyattck_data_models/technique.py
pyattck_data_models/tool.py
pyattck_data_models/types.py
pyattck_data_models-2.0.0.dist-info/entry_points.txt
pyattck_data_models-2.0.0.dist-info/LICENSE.rst
pyattck_data_models-2.0.0.dist-info/WHEEL
pyattck_data_models-2.0.0.dist-info/METADATA
pyattck_data_models-2.0.0.dist-info/RECORD
