Metadata-Version: 2.1
Name: pyattck-data-models
Version: 2.0.0
Summary: Pyattck Data models
Home-page: https://github.com/swimlane/pyattck-data-models
License: MIT
Author: Swimlane
Author-email: info@swimlane.com
Requires-Python: >=3.7,<4.0
Classifier: Development Status :: 3 - Alpha
Classifier: License :: OSI Approved :: MIT License
Classifier: Programming Language :: Python :: 3
Classifier: Programming Language :: Python :: 3.10
Classifier: Programming Language :: Python :: 3.7
Classifier: Programming Language :: Python :: 3.8
Classifier: Programming Language :: Python :: 3.9
Requires-Dist: attrs (>=21.4.0,<22.0.0)
Requires-Dist: click (>=8.0.1,<9.0.0)
Requires-Dist: pydantic (>=1.9.1,<2.0.0)
Project-URL: Changelog, https://github.com/swimlane/pyattck-data-models/releases
Project-URL: Documentation, https://pyattck-data-models.readthedocs.io
Project-URL: Repository, https://github.com/swimlane/pyattck-data-models
